priceloop_api/__init__.py
priceloop_api/auth.py
priceloop_api/client.py
priceloop_api/errors.py
priceloop_api/py.typed
priceloop_api/types.py
priceloop_api/api/__init__.py
priceloop_api/api/default/__init__.py
priceloop_api/api/default/add_data_column.py
priceloop_api/api/default/add_formula_column.py
priceloop_api/api/default/create_external_function.py
priceloop_api/api/default/create_workspace.py
priceloop_api/api/default/delete_external_function.py
priceloop_api/api/default/delete_table.py
priceloop_api/api/default/get_external_functions.py
priceloop_api/api/default/get_table.py
priceloop_api/api/default/get_table_data.py
priceloop_api/api/default/get_table_upload_csv_url.py
priceloop_api/api/default/get_workspace.py
priceloop_api/api/default/hello.py
priceloop_api/api/default/hello_auth.py
priceloop_api/api/default/list_workspaces.py
priceloop_api/api/default/update_column_position.py
priceloop_api/api/default/update_external_function.py
priceloop_api/models/__init__.py
priceloop_api/models/add_data_column_type.py
priceloop_api/models/api_column.py
priceloop_api/models/api_external_function.py
priceloop_api/models/api_table.py
priceloop_api/models/api_table_data.py
priceloop_api/models/api_workspace.py
priceloop_api/models/create_external_function_return_type.py
priceloop_api/models/create_external_function_runtime.py
priceloop_api/models/get_table_upload_csv_url_mode.py
priceloop_api/models/presigned_url.py
priceloop_api/models/table_row.py
priceloop_api/utils/__init__.py
priceloop_api/utils/utils.py
priceloop_api-1.0.2.dist-info/LICENSE
priceloop_api-1.0.2.dist-info/METADATA
priceloop_api-1.0.2.dist-info/WHEEL
priceloop_api-1.0.2.dist-info/top_level.txt
priceloop_api-1.0.2.dist-info/RECORD
