Metadata-Version: 2.1
Name: priceloop-api
Version: 1.0.2
Summary: A client library for accessing Priceloop API
Home-page: https://github.com/priceloop/priceloop-api-python
Author: Priceloop
Author-email: hello@priceloop.ai
Requires-Python: >=3.7, <4
License-File: LICENSE
Requires-Dist: httpx (<0.24.0,>=0.15.0)
Requires-Dist: attrs (>=21.3.0)
Requires-Dist: python-dateutil (<3,>=2.8.0)
Requires-Dist: boto3 (~=1.24.78)
Requires-Dist: requests (==2.25)
Requires-Dist: frozendict (==2.3.4)
Requires-Dist: pandas (==1.5.2)
